LICENSE
MANIFEST.in
README
energy.py
energytests.py
setup.py
energy.egg-info/PKG-INFO
energy.egg-info/SOURCES.txt
energy.egg-info/dependency_links.txt
energy.egg-info/requires.txt
energy.egg-info/top_level.txt